{
"ambientocclusion": false,
"textures": {
    "particle": "blocks/3dblocks/door_birch_lower",
    "down": "blocks/3dblocks/door_birch_lower",
    "up": "blocks/3dblocks/door_birch_lower",
    "north": "blocks/3dblocks/door_birch_lower",
    "south": "blocks/3dblocks/door_birch_lower",
    "west": "blocks/3dblocks/door_birch_lower",
    "east": "blocks/3dblocks/door_birch_lower_open"
},
"elements": [ 
{
    "__comment": "main*",
    "from": [ 2, 2, 0 ],
    "to": [ 2.5, 16, 1.5 ],
    "faces": {
        "down":  { "uv": [ 0, 16, 0.5, 14 ], "texture": "#down" },
        "up":    { "uv": [ 0, 14, 0.5, 16 ], "texture": "#up" },
        "north": { "uv": [ 15.5, 4.5, 16, 13.5 ], "texture": "#north" },
        "south": { "uv": [ 15.5, 4.5, 16, 13.5 ], "texture": "#south" },
        "west":  { "uv": [ 14, 0, 16, 14 ], "texture": "#west" },
        "east":  { "uv": [ 14, 2, 16, 14 ], "texture": "#east" }
    }
},
{
    "__comment": "main*",
    "from": [ 2, 2, 14.5 ],
    "to": [ 2.5, 16, 16 ],
    "faces": {
        "down":  { "uv": [ 0, 16, 0.5, 14 ], "texture": "#down" },
        "up":    { "uv": [ 0, 14, 0.5, 16 ], "texture": "#up" },
        "north": { "uv": [ 15.5, 4.5, 16, 13.5 ], "texture": "#north" },
        "south": { "uv": [ 15.5, 0, 16, 14 ], "texture": "#south" },
        "west":  { "uv": [ 14, 2, 16, 14 ], "texture": "#west" },
        "east":  { "uv": [ 0, 2, 2, 14 ], "texture": "#east" }
    }
},
{
    "__comment": "main*",
    "from": [ 2, 0, 0 ],
    "to": [ 2.5, 2, 16 ],
    "faces": {
        "down":  { "uv": [ 2.5, 16, 3, 0 ], "texture": "#down" },
        "up":    { "uv": [ 2.5, 13.5, 13.5, 14 ], "rotation": 90, "texture": "#up" },
        "north": { "uv": [ 15.5, 14, 16, 16 ], "texture": "#north" },
        "south": { "uv": [ 15.5, 14, 16, 16 ], "texture": "#south" },
        "west":  { "uv": [ 0, 14, 16, 16 ], "texture": "#west" },
        "east":  { "uv": [ 0, 14, 16, 16 ], "texture": "#east" }
    }
},
{
    "__comment": "main*",
    "from": [ 0, 2, 14.5 ],
    "to": [ 0.5, 16, 16 ],
    "faces": {
        "down":  { "uv": [ 0, 16, 0.5, 14 ], "texture": "#down" },
        "up":    { "uv": [ 0, 14, 0.5, 16 ], "texture": "#up" },
        "north": { "uv": [ 15.5, 4.5, 16, 13.5 ], "texture": "#north" },
        "south": { "uv": [ 15.5, 4.5, 16, 13.5 ], "texture": "#south" },
        "west":  { "uv": [ 14, 2, 16, 14 ], "texture": "#west" },
        "east":  { "uv": [ 0, 2, 2, 14 ], "texture": "#east" }
    }
},
{
    "__comment": "main*",
    "from": [ 0.5, 0, 0 ],
    "to": [ 2, 16, 16 ],
    "faces": {
        "down":  { "uv": [ 12, 16, 14, 0 ], "texture": "#down" },
        "up":    { "uv": [ 0.5, 0, 2.5, 16 ], "texture": "#up" },
        "north": { "uv": [ 14, 0, 16, 14.5 ], "texture": "#north" },
        "south": { "uv": [ 14, 0, 16, 14.5 ], "texture": "#south" },
        "west":  { "uv": [ 0, 0, 16, 16 ], "texture": "#west" },
        "east":  { "uv": [ 0, 0, 16, 16 ], "texture": "#east" }
    }
},
{
    "__comment": "main*",
    "from": [ 0, 0, 0 ],
    "to": [ 0.5, 2, 16 ],
    "faces": {
        "down":  { "uv": [ 3, 16, 3.5, 0 ], "texture": "#down" },
        "up":    { "uv": [ 2.5, 7, 13.5, 7.5 ], "rotation": 270, "texture": "#up" },
        "north": { "uv": [ 15.5, 14, 16, 16 ], "texture": "#north" },
        "south": { "uv": [ 15.5, 14, 16, 16 ], "texture": "#south" },
        "west":  { "uv": [ 0, 14, 16, 16 ], "texture": "#west" },
        "east":  { "uv": [ 0, 14, 16, 16 ], "texture": "#east" }
    }
},
{
    "__comment": "main*",
    "from": [ 0, 2, 6 ],
    "to": [ 0.5, 16, 10 ],
    "faces": {
        "down":  { "uv": [ 0, 10, 0.5, 6 ], "texture": "#down" },
        "up":    { "uv": [ 0, 6, 0.5, 10 ], "texture": "#up" },
        "north": { "uv": [ 5.5, 0, 6, 14 ], "texture": "#north" },
        "south": { "uv": [ 5.5, 0, 6, 14 ], "texture": "#south" },
        "west":  { "uv": [ 6, 0, 10, 14 ], "texture": "#west" },
        "east":  { "uv": [ 6, 0, 10, 14 ], "texture": "#east" }
    }
},
{
    "__comment": "main*",
    "from": [ 2, 0, 6 ],
    "to": [ 2.5, 16, 10 ],
    "faces": {
        "down":  { "uv": [ 2, 10, 2.5, 6 ], "texture": "#down" },
        "up":    { "uv": [ 2, 6, 2.5, 10 ], "texture": "#up" },
        "north": { "uv": [ 13.5, 0, 14, 16 ], "texture": "#north" },
        "south": { "uv": [ 13.5, 0, 14, 16 ], "texture": "#south" },
        "west":  { "uv": [ 6, 0, 10, 16 ], "texture": "#west" },
        "east":  { "uv": [ 6, 0, 10, 16 ], "texture": "#east" }
    }
},
{
    "__comment": "main*",
    "from": [ 0, 2, 0 ],
    "to": [ 0.5, 16, 1.5 ],
    "faces": {
        "down":  { "uv": [ 0, 2, 0.5, 0 ], "texture": "#down" },
        "up":    { "uv": [ 0, 0, 0.5, 2 ], "texture": "#up" },
        "north": { "uv": [ 15.5, 2, 16, 14 ], "texture": "#north" },
        "south": { "uv": [ 15.5, 4.5, 16, 14 ], "texture": "#south" },
        "west":  { "uv": [ 0, 2, 2, 14 ], "texture": "#west" },
        "east":  { "uv": [ 14, 2, 16, 14 ], "texture": "#east" }
    }
}
]
}